phun_reps/__init__.py
phun_reps/calc_presistent_diagram.py
phun_reps/feature_extraction.py
phun_reps/topology.py
phun_reps-0.1.2.dist-info/METADATA
phun_reps-0.1.2.dist-info/WHEEL
phun_reps-0.1.2.dist-info/top_level.txt
phun_reps-0.1.2.dist-info/RECORD
