Metadata-Version: 2.4
Name: phun_reps
Version: 0.1.2
Summary: A fun Python package for creating topological descriptors for nanoporous materials with persistent homology using nets (PHuN).
Author-email: Clara Kirkvold <c.m.kirkvold@bham.ac.uk>
License: MIT
Project-URL: Homepage, https://github.com/grynova-ccc/PHuN_Representations
Project-URL: Bug Tracker, https://github.com/grynova-ccc/PHuN_Representations/issues
Requires-Python: >=3.10
Requires-Dist: ase==3.26.0
Requires-Dist: Cython==3.2.0
Requires-Dist: juliacall==0.9.28
Requires-Dist: pandas==2.3.3
Requires-Dist: ripser==0.6.12
